privacy/qa/__init__.py
privacy.qa-0.0.1.dist-info/METADATA
privacy.qa-0.0.1.dist-info/WHEEL
privacy.qa-0.0.1.dist-info/top_level.txt
privacy.qa-0.0.1.dist-info/RECORD
